<?xml version="1.0" encoding="utf-8" ?>
<Defs>
	<!-- ==========[ESCP_DunmerCulture]========== -->
	<CultureDef>
		<defName>ESCP_DunmerCulture</defName>
		<label>Dunmeri</label>
		<description>An ancient culture common among Dunmer Great Houses.</description>
		<pawnNameMaker>ESCP_Dunmer_NamerMale</pawnNameMaker>
		<pawnNameMakerFemale>ESCP_Dunmer_NamerFemale</pawnNameMakerFemale>
		<ideoNameMaker MayRequire="Ludeon.RimWorld.Ideology">NamerIdeoCorunan</ideoNameMaker>
		<deityNameMaker MayRequire="Ludeon.RimWorld.Ideology">ESCP_Dunmer_NamerCultureDeityName</deityNameMaker>
		<deityTypeMaker MayRequire="Ludeon.RimWorld.Ideology">DeityTypeMakerCorunan</deityTypeMaker>
		<festivalNameMaker MayRequire="Ludeon.RimWorld.Ideology">NamerFestivalCorunan</festivalNameMaker>
		<leaderTitleMaker MayRequire="Ludeon.RimWorld.Ideology">ESCP_Dunmer_NamerCultureLeaderTitle</leaderTitleMaker>
		<allowedPlaceTags>
			<li>OriginTribal</li>
		</allowedPlaceTags>
		<iconPath>World/WorldObjects/Expanding/ESCP_DunmerSettlementHonourable</iconPath>
		<preferredWeaponClasses>
			<noble>MeleePiercer</noble>
			<despised>MeleeBlunt</despised>
		</preferredWeaponClasses>
		<thingStyleCategories>
			<li MayRequire="Ludeon.RimWorld.Ideology">
				<category>ESCP_DunmerStyle</category>
				<priority>4</priority>
			</li>
			<li MayRequire="Ludeon.RimWorld.Ideology">
				<category>Rustic</category>
				<priority>1</priority>
			</li>
			<li MayRequire="Ludeon.RimWorld.Ideology">
				<category>Morbid</category>
				<priority>1</priority>
			</li>
		</thingStyleCategories>
		<styleItemTags>
			<li>
				<tag>ESCP_TattooFaceDunmer</tag>
				<baseWeight>1</baseWeight>
				<weightFactor>1</weightFactor>
			</li>
			<li>
				<tag>Medieval</tag>
				<baseWeight>1</baseWeight>
				<weightFactor>1</weightFactor>
			</li>
			<li>
				<tag>Tribal</tag>
				<baseWeight>1</baseWeight>
				<weightFactor>1</weightFactor>
			</li>
			<li>
				<tag>NoBeard</tag>
				<baseWeight>10</baseWeight>
				<weightFactor>1</weightFactor>
			</li>
			<li>
				<tag>BeardTribal</tag>
				<baseWeight>0.3</baseWeight>
				<weightFactor>1</weightFactor>
			</li>
			<li>
				<tag>TattooFaceTribal</tag>
				<baseWeight>0.4</baseWeight>
				<weightFactor>1</weightFactor>
			</li>
			<li>
				<tag>TattooBodyTribal</tag>
				<baseWeight>0.4</baseWeight>
				<weightFactor>1</weightFactor>
			</li>
			<li>
				<tag>NoTattoo</tag>
				<baseWeight>1</baseWeight>
				<weightFactor>1</weightFactor>
			</li>
		</styleItemTags>
	</CultureDef>
	<!-- ==========[ESCP_DunmerAshlanderCulture]========== -->
	<CultureDef>
		<defName>ESCP_DunmerAshlanderCulture</defName>
		<label>Dunmer Ashlander</label>
		<description>An ancient culture common among Dunmer Ashlander Tribes.</description>
		<pawnNameMaker>ESCP_DunmerAshlander_NamerMale</pawnNameMaker>
		<pawnNameMakerFemale>ESCP_DunmerAshlander_NamerFemale</pawnNameMakerFemale>
		<ideoNameMaker MayRequire="Ludeon.RimWorld.Ideology">NamerIdeoCorunan</ideoNameMaker>
		<deityNameMaker MayRequire="Ludeon.RimWorld.Ideology">ESCP_DunmerAshlander_NamerCultureDeityName</deityNameMaker>
		<deityTypeMaker MayRequire="Ludeon.RimWorld.Ideology">DeityTypeMakerCorunan</deityTypeMaker>
		<festivalNameMaker MayRequire="Ludeon.RimWorld.Ideology">NamerFestivalCorunan</festivalNameMaker>
		<leaderTitleMaker MayRequire="Ludeon.RimWorld.Ideology">ESCP_DunmerAshlander_NamerCultureLeaderTitle</leaderTitleMaker>
		<allowedPlaceTags>
			<li>OriginTribal</li>
		</allowedPlaceTags>
		<iconPath>World/WorldObjects/Expanding/ESCP_DunmerAshlanderSettlement</iconPath>
		<preferredWeaponClasses>
			<noble>MeleePiercer</noble>
			<despised>MeleeBlunt</despised>
		</preferredWeaponClasses>
		<thingStyleCategories>
			<li MayRequire="Ludeon.RimWorld.Ideology">
				<category>ESCP_DunmerAshlanderStyle</category>
				<priority>4</priority>
			</li>
			<li MayRequire="Ludeon.RimWorld.Ideology">
				<category>Rustic</category>
				<priority>1</priority>
			</li>
		</thingStyleCategories>
		<styleItemTags>
			<li>
				<tag>ESCP_TattooFaceAshlander</tag>
				<baseWeight>1</baseWeight>
				<weightFactor>1</weightFactor>
			</li>
			<li>
				<tag>Tribal</tag>
				<baseWeight>1</baseWeight>
				<weightFactor>1</weightFactor>
			</li>
			<li>
				<tag>NoBeard</tag>
				<baseWeight>10</baseWeight>
				<weightFactor>1</weightFactor>
			</li>
			<li>
				<tag>BeardTribal</tag>
				<baseWeight>0.3</baseWeight>
				<weightFactor>1</weightFactor>
			</li>
			<li>
				<tag>TattooFaceTribal</tag>
				<baseWeight>0.4</baseWeight>
				<weightFactor>1</weightFactor>
			</li>
			<li>
				<tag>TattooBodyTribal</tag>
				<baseWeight>0.4</baseWeight>
				<weightFactor>1</weightFactor>
			</li>
			<li>
				<tag>NoTattoo</tag>
				<baseWeight>1</baseWeight>
				<weightFactor>1</weightFactor>
			</li>
		</styleItemTags>
	</CultureDef>
</Defs>
